d2grid/__init__.py
d2grid/__main__.py
d2grid/generator/__init__.py
d2grid/generator/grid_generator.py
d2grid/generator/settings_model.py
d2grid/main.py
d2grid/sources/__init__.py
d2grid/sources/attr/__init__.py
d2grid/sources/attr/model.py
d2grid/sources/attr/source.py
d2grid/sources/file/__init__.py
d2grid/sources/file/model.py
d2grid/sources/file/source.py
d2grid/sources/spectral/__init__.py
d2grid/sources/spectral/model.py
d2grid/sources/spectral/source.py
d2grid/sources/stratz/__init__.py
d2grid/sources/stratz/model.py
d2grid/sources/stratz/source.py
d2grid/utils.py
d2grid-0.2.0.dist-info/licenses/LICENSE
d2grid-0.2.0.dist-info/WHEEL
d2grid-0.2.0.dist-info/entry_points.txt
d2grid-0.2.0.dist-info/METADATA
d2grid-0.2.0.dist-info/RECORD
