Metadata-Version: 2.4
Name: d2grid
Version: 0.2.0
Summary: Highly customizable Dota 2 hero grid generator
Keywords: dota,config,generator,hero,grid,layout
Author: Denys Vasylyshyn
Author-email: Denys Vasylyshyn <denys.mkk@gmail.com>
License-Expression: AGPL-3.0-only
License-File: LICENSE
Classifier: Topic :: Utilities
Classifier: Intended Audience :: End Users/Desktop
Classifier: License :: OSI Approved :: GNU Affero General Public License v3
Classifier: Operating System :: OS Independent
Classifier: Programming Language :: Python :: 3
Classifier: Programming Language :: Python :: 3.14
Classifier: Framework :: Pydantic :: 2
Classifier: Typing :: Typed
Requires-Dist: httpx>=0.28.1
Requires-Dist: pydantic>=2.12.0
Requires-Python: >=3.14
Project-URL: Repository, https://github.com/mkk5/d2grid
